fatek/__init__.py
fatek/errors.py
fatek/fatek.py
fatek/symbol.py
fatek/target.py
fatek_fbs_lib-0.1.9.data/scripts/fatek-cli
tests/__init__.py
tests/test_fatek.py
tests/test_symbol.py
tests/test_target.py
fatek_fbs_lib-0.1.9.dist-info/METADATA
fatek_fbs_lib-0.1.9.dist-info/WHEEL
fatek_fbs_lib-0.1.9.dist-info/top_level.txt
fatek_fbs_lib-0.1.9.dist-info/RECORD
